main.py
mainan.py
rumus_matematika.py
pedophilia-0.1.0.dist-info/METADATA
pedophilia-0.1.0.dist-info/WHEEL
pedophilia-0.1.0.dist-info/top_level.txt
pedophilia-0.1.0.dist-info/RECORD
