Metadata-Version: 2.2
Name: pedophilia
Version: 0.1.0
Summary: Add your description here
Requires-Python: >=3.13
Requires-Dist: numpy>=2.2.3
Requires-Dist: testicles>=0.1.0
